{
  "_fv": 85,
  "_type": "recipe",
  "definition": {
    "recipeType": "Smelting",
    "recipeRetstackSize": 1,
    "group": "",
    "unlockingItems": [
      {
        "value": "CUSTOM:RawPlatinum"
      }
    ],
    "cookingBookCategory": "MISC",
    "xpReward": 1.0,
    "cookingTime": 190,
    "craftingBookCategory": "MISC",
    "recipeShapeless": false,
    "smeltingInputStack": {
      "value": "CUSTOM:RawPlatinum"
    },
    "smeltingReturnStack": {
      "value": "CUSTOM:Platinum"
    },
    "name": "platinumsmelting",
    "namespace": "mod"
  }
}